<?xml version="1.0" encoding="utf-8"?>
<!DOCTYPE hibernate-mapping PUBLIC "-//Hibernate/Hibernate Mapping DTD 3.0//EN"
"http://hibernate.sourceforge.net/hibernate-mapping-3.0.dtd">
<!-- 
    Mapping file autogenerated by MyEclipse Persistence Tools
-->
<hibernate-mapping>
    <class name="com.xxmodd.entity.Admin" table="admin" catalog="stu_manager">
        <id name="admId" type="java.lang.Integer">
            <column name="adm_id" />
            <generator class="uuid" />
        </id>
        <property name="admPsw" type="java.lang.String">
            <column name="adm_psw" length="32" />
        </property>
    </class>
</hibernate-mapping>
